{"cameraMode":{"drawMode":0,"name":"Shaded","section":"Shading Mode"},"sceneLighting":true,"audioPlay":false,"sceneViewState":{"m_AlwaysRefresh":false,"showFog":true,"showSkybox":true,"showFlares":true,"showImageEffects":true,"showParticleSystems":true,"showVisualEffectGraphs":true,"m_FxEnabled":true},"in2DMode":false,"pivot":{"x":359.7119140625,"y":1049.8851318359375,"z":37.96484375},"rotation":{"x":-0.08510679751634598,"y":-0.002693542977795005,"z":0.00023190639331005514,"w":-0.9963827729225159},"size":1344.5908203125,"orthographic":false}